{
  "$schema": "http://cyclonedx.org/schema/bom-1.4.schema.json",
  "bomFormat": "CycloneDX",
  "specVersion": "1.4",
  "serialNumber": "urn:uuid:6d9956e8-5b3f-4cbc-ba76-fa6f0e7b262f",
  "version": 1,
  "metadata": {
    "timestamp": "2023-01-02T18:46:16.585255+00:00",
    "tools": [
      {
        "vendor": "CycloneDX",
        "name": "cyclonedx-bom",
        "version": "3.10.1"
      },
      {
        "vendor": "CycloneDX",
        "name": "cyclonedx-python-lib",
        "version": "3.1.1",
        "externalReferences": [
          {
            "url": "https://github.com/CycloneDX/cyclonedx-python-lib/actions",
            "type": "build-system"
          },
          {
            "url": "https://pypi.org/project/cyclonedx-python-lib/",
            "type": "distribution"
          },
          {
            "url": "https://cyclonedx.github.io/cyclonedx-python-lib/",
            "type": "documentation"
          },
          {
            "url": "https://github.com/CycloneDX/cyclonedx-python-lib/issues",
            "type": "issue-tracker"
          },
          {
            "url": "https://github.com/CycloneDX/cyclonedx-python-lib/blob/main/LICENSE",
            "type": "license"
          },
          {
            "url": "https://github.com/CycloneDX/cyclonedx-python-lib/blob/main/CHANGELOG.md",
            "type": "release-notes"
          },
          {
            "url": "https://github.com/CycloneDX/cyclonedx-python-lib",
            "type": "vcs"
          },
          {
            "url": "https://cyclonedx.org",
            "type": "website"
          }
        ]
      }
    ]
  },
  "components": [
    {
      "type": "library",
      "bom-ref": "37f54cf8-a9e2-47f2-851a-94697d69cd79",
      "name": "jsonschema",
      "version": "4.17.3",
      "purl": "pkg:pypi/jsonschema@4.17.3"
    },
    {
      "type": "library",
      "bom-ref": "2c8a29ab-c1a1-4812-bfe4-27006d0cb997",
      "name": "typer",
      "version": "0.7.0",
      "purl": "pkg:pypi/typer@0.7.0"
    },
    {
      "type": "library",
      "bom-ref": "069f0482-ac87-483e-a33f-3507db21466c",
      "name": "xmlschema",
      "version": "2.1.1",
      "purl": "pkg:pypi/xmlschema@2.1.1"
    }
  ],
  "dependencies": [
    {
      "ref": "37f54cf8-a9e2-47f2-851a-94697d69cd79",
      "dependsOn": []
    },
    {
      "ref": "2c8a29ab-c1a1-4812-bfe4-27006d0cb997",
      "dependsOn": []
    },
    {
      "ref": "069f0482-ac87-483e-a33f-3507db21466c",
      "dependsOn": []
    }
  ]
}
